open_github_pkg/__init__.py
open_github-2.0.0.dist-info/LICENSE
open_github-2.0.0.dist-info/METADATA
open_github-2.0.0.dist-info/WHEEL
open_github-2.0.0.dist-info/top_level.txt
open_github-2.0.0.dist-info/RECORD
